cognito_ses_domain/__init__.py
cognito_ses_domain/py.typed
cognito_ses_domain/_jsii/__init__.py
cognito_ses_domain/_jsii/cognito-ses-domain@0.0.0.jsii.tgz
cognito_ses_domain-0.0.0.dist-info/LICENSE
cognito_ses_domain-0.0.0.dist-info/METADATA
cognito_ses_domain-0.0.0.dist-info/WHEEL
cognito_ses_domain-0.0.0.dist-info/top_level.txt
cognito_ses_domain-0.0.0.dist-info/RECORD
