Metadata-Version: 2.1
Name: cognito-ses-domain
Version: 0.0.0
Summary: cognito-ses-domain
Home-page: https://github.com/pablocano/cognito-ses-domain.git
Author: Pablo Cano<pablo.cano@merapar.com>
License: MIT
Project-URL: Source, https://github.com/pablocano/cognito-ses-domain.git
Classifier: Intended Audience :: Developers
Classifier: Operating System :: OS Independent
Classifier: Programming Language :: JavaScript
Classifier: Programming Language :: Python :: 3 :: Only
Classifier: Programming Language :: Python :: 3.9
Classifier: Programming Language :: Python :: 3.10
Classifier: Programming Language :: Python :: 3.11
Classifier: Typing :: Typed
Classifier: Development Status :: 5 - Production/Stable
Classifier: License :: OSI Approved
Requires-Python: ~=3.9
License-File: LICENSE
Requires-Dist: aws-cdk-lib <3.0.0,>=2.200.0
Requires-Dist: constructs <11.0.0,>=10.0.5
Requires-Dist: jsii <2.0.0,>=1.113.0
Requires-Dist: publication >=0.0.3
Requires-Dist: ses-cloudwatch <2.0.0,>=1.2.1
Requires-Dist: typeguard <4.3.0,>=2.13.3
